pycodehash/__init__.py
pycodehash/hashing.py
pycodehash/version.py
pycodehash/datasets/__init__.py
pycodehash/datasets/_s3_client.py
pycodehash/datasets/approximate_hasher.py
pycodehash/datasets/hive.py
pycodehash/datasets/local.py
pycodehash/datasets/python.py
pycodehash/datasets/s3.py
pycodehash/dependency/__init__.py
pycodehash/dependency/dependency.py
pycodehash/python_function/__init__.py
pycodehash/python_function/decorator_stripper.py
pycodehash/python_function/docstring_stripper.py
pycodehash/python_function/function_stripper.py
pycodehash/python_function/hashing.py
pycodehash/python_function/ruff_processor.py
pycodehash/python_function/ruff_project_processor.py
pycodehash/python_function/source_processor.py
pycodehash/python_function/stores.py
pycodehash/python_function/tracing.py
pycodehash/python_function/transfomers.py
pycodehash/python_function/typehint_stripper.py
pycodehash/python_function/unparse.py
pycodehash/python_function/utils.py
pycodehash/python_function/whitespace_normalizer.py
pycodehash/python_module/__init__.py
pycodehash/python_module/import_visitor.py
pycodehash/python_module/python_module_hasher.py
pycodehash/sql/__init__.py
pycodehash/sql/ast_transformer.py
pycodehash/sql/ast_visitor.py
pycodehash/sql/comment_filter.py
pycodehash/sql/default_database_filter.py
pycodehash/sql/references.py
pycodehash/sql/sql_hasher.py
pycodehash/sql/whitespace_filter.py
pycodehash-0.7.0.dist-info/METADATA
pycodehash-0.7.0.dist-info/WHEEL
pycodehash-0.7.0.dist-info/licenses/LICENSE
pycodehash-0.7.0.dist-info/RECORD
