Metadata-Version: 2.3
Name: pycodehash
Version: 0.7.0
Project-URL: Source, https://github.com/pycodehash/pycodehash
Project-URL: Documentation, https://github.com/pycodehash/pycodehash#readme
Project-URL: Issues, https://github.com/pycodehash/pycodehash/issues
Author-email: Max Baak <maxbaak@gmail.com>, Simon Brugman <sfbbrugman@gmail.com>, Ralph Urlus <rurlus.dev@gmail.com>
License: MIT License
License-File: LICENSE
Classifier: Programming Language :: Python :: 3
Requires-Python: >=3.8
Requires-Dist: asttokens
Requires-Dist: astunparse; python_version <= '3.9'
Requires-Dist: rope
Requires-Dist: ruff==0.6.3
Requires-Dist: typing-extensions; python_version <= '3.11'
Provides-Extra: docs
Requires-Dist: mkdocs; extra == 'docs'
Requires-Dist: mkdocs-macros-plugin; extra == 'docs'
Provides-Extra: s3
Requires-Dist: boto3; extra == 's3'
Provides-Extra: sql
Requires-Dist: sqlfluff; extra == 'sql'
Requires-Dist: sqllineage; extra == 'sql'
Provides-Extra: test
Requires-Dist: boto3; extra == 'test'
Requires-Dist: moto[s3]<6,>=5; extra == 'test'
Requires-Dist: pytest; extra == 'test'
Requires-Dist: pytest-cov; extra == 'test'
Requires-Dist: sqlfluff; extra == 'test'
Requires-Dist: sqllineage; extra == 'test'
